{
  "id": "288d5772-7d7d-43b4-8281-c54a290897ef",
  "name": "tslint-report",
  "friendlyName": "tslint-report",
  "description": "tslint report result",
  "helpMarkDown": "",
  "category": "Utility",
  "author": "miguel-savignano",
  "version": {
    "Major": 0,
    "Minor": 1,
    "Patch": 0
  },
  "instanceNameFormat": "TSLint report",
  "inputs": [
    {
      "name": "filePath",
      "type": "filePath",
      "label": "TSlint result file",
      "defaultValue": "tslint-result.json",
      "required": true,
      "helpMarkDown": "TSlint result file"
    }
  ],
  "execution": {
    "Node": {
      "target": "index.js"
    }
  }
}
